suskabot/__init__.py
suskabot/__main__.py
suskabot/app/__init__.py
suskabot/app/app.py
suskabot/config/.env.example
suskabot/config/.gitignore
suskabot/config/__init__.py
suskabot/config/config.py
suskabot/controllers/__init__.py
suskabot/controllers/telegram_api/__init__.py
suskabot/controllers/telegram_api/bot.py
suskabot/controllers/telegram_api/handlers/__init__.py
suskabot/controllers/telegram_api/handlers/app.py
suskabot/controllers/telegram_api/handlers/translator.py
suskabot/controllers/telegram_api/handlers/youtube_downloader.py
suskabot/services/__init__.py
suskabot/services/translator.py
suskabot/services/youtube_downloader.py
suskabot/tests/test_youtube_downloader.py
suskabot/utils/__init__.py
suskabot/utils/utils.py
suskabot-0.2.4.dist-info/LICENSE
suskabot-0.2.4.dist-info/METADATA
suskabot-0.2.4.dist-info/WHEEL
suskabot-0.2.4.dist-info/RECORD
