Metadata-Version: 2.1
Name: suskabot
Version: 0.2.4
Summary: telegram bot with various functions
License: LICENSE
Author: vinyl_summer
Author-email: vinyl6428@gmail.dotcom
Requires-Python: >=3.11,<4.0
Classifier: License :: Other/Proprietary License
Classifier: Programming Language :: Python :: 3
Classifier: Programming Language :: Python :: 3.11
Classifier: Programming Language :: Python :: 3.12
Requires-Dist: lingua-language-detector (>=2.0.2,<3.0.0)
Requires-Dist: pydantic (>=2.7.1,<3.0.0)
Requires-Dist: python-dotenv (>=1.0.1,<2.0.0)
Requires-Dist: python-telegram-bot[job-queue] (>=21.1.1,<22.0.0)
Requires-Dist: pytube (==15.0.2)
Requires-Dist: translators (>=5.9.1,<6.0.0)
